LICENSE
README.md
setup.py
hipsofcobra/__init__.py
hipsofcobra/classes.py
hipsofcobra.egg-info/PKG-INFO
hipsofcobra.egg-info/SOURCES.txt
hipsofcobra.egg-info/dependency_links.txt
hipsofcobra.egg-info/requires.txt
hipsofcobra.egg-info/top_level.txt
hipsofcobra/input/hips_c1.txt
hipsofcobra/input/hips_c2.txt
hipsofcobra/input/hips_d1.txt
hipsofcobra/input/hips_d2.txt