Metadata-Version: 2.1
Name: hipsofcobra
Version: 0.0.7
Summary: A package for calculating the branching ratios of a scalar decaying to pi  and K mesons from a coupled-channel analysis.
Home-page: UNKNOWN
Author: Patrick Blackstone (@blackstonep)
Author-email: <blackstonep924@gmail.com>
License: UNKNOWN
Keywords: python,physics,hep
Platform: UNKNOWN
License-File: LICENSE
